webauthn/__init__.py
webauthn/attestation.py
webauthn/data.py
webauthn/errors.py
webauthn/metadata.py
webauthn/types.py
webauthn/utils.py
py_webauthn-0.0.4.dist-info/LICENSE.md
py_webauthn-0.0.4.dist-info/METADATA
py_webauthn-0.0.4.dist-info/WHEEL
py_webauthn-0.0.4.dist-info/top_level.txt
py_webauthn-0.0.4.dist-info/RECORD
