Metadata-Version: 2.1
Name: py-webauthn
Version: 0.0.4
Summary: Server side WebAuthn handling, with support for FaceID and FIDO metadata
Home-page: https://github.com/as207960/python-webauthn
Author: AS207960 Cyfyngedig
Author-email: hello@glauca.digital
License: UNKNOWN
Project-URL: Bug Tracker, https://github.com/as207960/python-webauthn/issues
Platform: UNKNOWN
Classifier: Programming Language :: Python :: 3
Classifier: License :: OSI Approved :: MIT License
Classifier: Operating System :: OS Independent
Requires-Python: >=3.6
License-File: LICENSE.md
